JsdLibrary/__init__.py
JsdLibrary/jsd.py
JsdLibrary/version.py
robotframework_jsd-0.1.3.dist-info/METADATA
robotframework_jsd-0.1.3.dist-info/WHEEL
robotframework_jsd-0.1.3.dist-info/top_level.txt
robotframework_jsd-0.1.3.dist-info/RECORD
