Metadata-Version: 2.1
Name: robotframework-jsd
Version: 0.1.3
Summary: JSD validator for robotframework
Home-page: UNKNOWN
Author: mangobowl
Author-email: mangobowl@163.com
License: BSD License
Keywords: robotframework testing test automation json json-schema
Platform: any
Classifier: Development Status :: 5 - Production/Stable
Classifier: License :: OSI Approved :: BSD License
Classifier: Operating System :: OS Independent
Classifier: Programming Language :: Python
Classifier: Topic :: Software Development :: Testing
Requires-Dist: robotframework
Requires-Dist: jsonschema
